budgetscribe/__init__.py
budgetscribe/main.py
budgetscribe/prompts.py
budgetscribe-2025.12.21124349.dist-info/METADATA
budgetscribe-2025.12.21124349.dist-info/WHEEL
budgetscribe-2025.12.21124349.dist-info/top_level.txt
budgetscribe-2025.12.21124349.dist-info/RECORD
