Metadata-Version: 2.4
Name: budgetscribe
Version: 2025.12.21124349
Summary: A new package that analyzes user-provided text descriptions of their monthly expenses and income to generate a structured affordability assessment. It categorizes spending, identifies potential saving
Author-email: budgetscribe <hi@eugene.plus>
License: MIT
Project-URL: Homepage, https://github.com/chigwell/budgetscribe
Requires-Python: >=3.9
Requires-Dist: langchain-llm7>=0.0.0
Requires-Dist: llmatch-messages>=0.0.0
Requires-Dist: langchain-core>=0.3.0
